image_processing/__init__.py
image_processing/imgs/__init__.py
image_processing/imgs/imagem1.jpg
image_processing/imgs/imagem2.jpg
image_processing/processing/__init__.py
image_processing/processing/combination.py
image_processing/processing/transformation.py
image_processing/tests/__init__.py
image_processing/tests/test_image.py
image_processing/tests/test_image_processing.py
image_processing/tests/test_processing.py
image_processing/tests/test_utils.py
image_processing/utils/__init__.py
image_processing/utils/io.py
image_processing/utils/plot.py
image_processing_navpack-0.2.7.dist-info/METADATA
image_processing_navpack-0.2.7.dist-info/WHEEL
image_processing_navpack-0.2.7.dist-info/entry_points.txt
image_processing_navpack-0.2.7.dist-info/top_level.txt
image_processing_navpack-0.2.7.dist-info/RECORD
