Metadata-Version: 2.1
Name: image_processing_navpack
Version: 0.2.7
Summary: A package for processing and analyzing images.
Author: Fabiano
Author-email: nav.info.suporte@gmail.com
License: MIT
Project-URL: Source, https://github.com/Fabianonavarro/image_processing_navpack.git
Project-URL: Documentation, https://github.com/Fabianonavarro/image_processing_navpack/blob/main/README.md
Classifier: Development Status :: 3 - Alpha
Classifier: Intended Audience :: Developers
Classifier: License :: OSI Approved :: MIT License
Classifier: Programming Language :: Python :: 3
Classifier: Programming Language :: Python :: 3.9
Classifier: Programming Language :: Python :: 3.10
Classifier: Programming Language :: Python :: 3.11
Requires-Dist: numpy>=1.26.4
Requires-Dist: matplotlib>=3.9.2
Requires-Dist: scikit-image>=0.24.0
Requires-Dist: imageio>=2.35.1
Provides-Extra: dev
Requires-Dist: pytest>=8.3.2; extra == "dev"
